{
    "hash": "0x2e39bb40933e751bce41f58abf36bd93330d513e8732a1b8cae189316c63ad55",
    "chain": "Ethereum",
    "U": [
        0,
        1
    ],
    "V": [
        1,
        2
    ],
    "feat": [
        [
            0,
            0,
            0,
            1,
            0.0,
            0.5,
            0.0,
            0.5,
            -1.0
        ],
        [
            0,
            0,
            0,
            1,
            0.5,
            0.5,
            0.5,
            0.5,
            0.0
        ],
        [
            0,
            0,
            1,
            0,
            0.5,
            0.0,
            0.5,
            0.0,
            1.0
        ]
    ],
    "nodeCount": 3,
    "edgeCount": 2,
    "tokenCount": 2,
    "nodes": [
        "0x0000000000000000000000000000000000000000",
        "0x50ef16a9167661dc2500ddde8f83937c1ba4cd5f",
        "0x1d50c4f18d7af4fce2ea93c7942aae6260788596"
    ],
    "tokens": [
        "0x1d50c4f18d7af4fce2ea93c7942aae6260788596",
        "0x6b175474e89094c44da98b954eedeac495271d0f"
    ]
}