{
    "hash": "0x5c8980a2c5d210073d2a8697c3d50a0d50f6a09ada8630bdd9f7ed32ae28bb59",
    "chain": "Binance",
    "U": [
        0,
        0,
        2,
        4,
        3,
        3,
        0,
        0,
        2,
        6,
        0,
        6,
        6,
        0,
        4,
        6,
        6,
        6,
        0,
        3,
        7,
        8,
        9,
        11,
        10,
        8,
        10,
        10,
        12,
        8,
        8,
        10,
        10,
        0,
        10,
        7,
        0,
        7,
        0,
        7,
        3
    ],
    "V": [
        1,
        2,
        3,
        3,
        5,
        6,
        1,
        2,
        6,
        4,
        6,
        0,
        4,
        6,
        6,
        0,
        3,
        0,
        6,
        7,
        8,
        9,
        10,
        10,
        8,
        10,
        11,
        12,
        8,
        10,
        12,
        11,
        12,
        7,
        8,
        13,
        7,
        5,
        7,
        13,
        5
    ],
    "feat": [
        [
            0,
            0,
            0,
            1,
            0.07317073170731707,
            0.24390243902439024,
            0.14285714285714285,
            0.5714285714285714,
            -4.123195467069655
        ],
        [
            0,
            0,
            0,
            1,
            0.04878048780487805,
            0.0,
            0.14285714285714285,
            0.0,
            0.07724894272701746
        ],
        [
            0,
            0,
            1,
            0,
            0.04878048780487805,
            0.04878048780487805,
            0.14285714285714285,
            0.14285714285714285,
            -0.35096874067497286
        ],
        [
            0,
            1,
            0,
            0,
            0.07317073170731707,
            0.0975609756097561,
            0.2857142857142857,
            0.2857142857142857,
            -1.1071313543676783e-16
        ],
        [
            0,
            1,
            0,
            0,
            0.04878048780487805,
            0.04878048780487805,
            0.14285714285714285,
            0.2857142857142857,
            0.12345709707286712
        ],
        [
            0,
            0,
            0,
            1,
            0.07317073170731707,
            0.0,
            0.42857142857142855,
            0.0,
            2.0000007496105963
        ],
        [
            0,
            1,
            0,
            0,
            0.14634146341463414,
            0.14634146341463414,
            0.2857142857142857,
            0.2857142857142857,
            1.123457097072867
        ],
        [
            0,
            1,
            0,
            0,
            0.0975609756097561,
            0.0975609756097561,
            0.42857142857142855,
            0.42857142857142855,
            -8.326672684688674e-17
        ],
        [
            0,
            1,
            0,
            0,
            0.0975609756097561,
            0.0975609756097561,
            0.42857142857142855,
            0.42857142857142855,
            0.0010000000024129512
        ],
        [
            0,
            0,
            1,
            0,
            0.024390243902439025,
            0.024390243902439025,
            0.14285714285714285,
            0.14285714285714285,
            -0.999999678738316
        ],
        [
            0,
            1,
            0,
            0,
            0.0975609756097561,
            0.14634146341463414,
            0.2857142857142857,
            0.2857142857142857,
            0.001000000002412571
        ],
        [
            0,
            0,
            1,
            0,
            0.04878048780487805,
            0.024390243902439025,
            0.14285714285714285,
            0.14285714285714285,
            -0.0010000000024128486
        ],
        [
            0,
            0,
            1,
            0,
            0.07317073170731707,
            0.024390243902439025,
            0.2857142857142857,
            0.14285714285714285,
            0.9989999999975872
        ],
        [
            0,
            1,
            0,
            0,
            0.04878048780487805,
            0.0,
            0.2857142857142857,
            0.0,
            1.1499999999995958
        ]
    ],
    "nodeCount": 14,
    "edgeCount": 41,
    "tokenCount": 7,
    "nodes": [
        "0x0000000000000000000000000000000000000000",
        "0xd4cfec77cdc21573982ec85cf33cfde6cc677e74",
        "0x009cf7bc57584b7998236eff51b98a168dcea9b0",
        "0xe07bdaac4573a00208d148bd5b3e5d2ae4ebd0cc",
        "0x73feaa1ee314f8c655e354234017be2193c9e24e",
        "0x5fc975b2f9e07ff59b0ba5feee666b2459320b8f",
        "0xedfcb78e73f7ba6ad2d829bf5d462a0924da28ed",
        "0x8cb88701790f650f273c8bb2cc4c5f439cd65219",
        "0xcbec8e7ab969f6eb873df63d04b4eafc353574b1",
        "0xa527a61703d82139f8a06bc30097cc9caa2df5a6",
        "0x05ff2b0db69458a0750badebc4f9e13add608c7f",
        "0xbb4cdb9cbd36b01bd1cbaebf2de08d9173bc095c",
        "0x7bb89460599dbf32ee3aa50798bbceae2a5f7f6a",
        "0xcadc8cb26c8c7cb46500e61171b5f27e9bd7889d"
    ],
    "tokens": [
        "0x0e09fabb73bd3ade0a17ecc321fd13a19e81ce82",
        "0x20bcc3b8a0091ddac2d0bc30f68e6cbb97de59cd",
        "0x009cf7bc57584b7998236eff51b98a168dcea9b0",
        "0xbb4cdb9cbd36b01bd1cbaebf2de08d9173bc095c",
        "native_token",
        "0xc9849e6fdb743d08faee3e34dd2d1bc69ea11a51",
        "0x7bb89460599dbf32ee3aa50798bbceae2a5f7f6a"
    ]
}