{
    "hash": "0x6037ca926688d7f06587b4e6fff2f2c9d5e8e042a21ff2c92b1865465ecc4284",
    "chain": "Ethereum",
    "U": [
        0,
        0,
        1,
        1,
        1,
        1,
        1,
        1,
        1,
        1,
        1,
        1,
        1,
        1,
        1,
        1,
        1,
        1,
        1,
        1,
        1,
        1,
        1,
        1,
        1,
        1,
        1,
        1,
        1,
        1,
        1,
        1,
        1,
        1,
        1,
        1,
        1,
        1,
        1,
        1,
        1,
        1,
        1,
        1,
        1,
        1,
        1,
        1,
        1,
        1,
        1,
        1,
        1,
        1,
        1,
        1,
        1,
        1,
        1,
        1,
        1,
        1,
        1,
        1,
        1,
        1,
        1,
        1,
        1,
        1,
        1,
        1,
        1,
        1,
        1,
        1,
        1,
        1,
        1,
        1,
        1,
        1,
        1,
        1,
        1,
        1,
        1,
        1,
        1,
        1,
        1,
        1,
        1,
        1,
        1,
        1,
        1,
        1,
        1,
        1,
        1,
        1,
        1,
        1,
        1,
        1,
        1,
        1,
        1,
        1,
        1,
        1,
        1,
        1,
        1,
        1,
        1,
        1,
        1,
        1,
        1,
        1,
        1,
        1,
        1,
        1,
        1,
        1,
        1,
        1,
        1,
        1,
        1,
        1,
        1,
        1,
        1,
        1,
        1,
        1,
        1,
        1,
        1,
        1,
        1,
        1,
        1,
        1,
        1,
        1,
        1,
        1,
        1,
        1,
        1,
        1,
        1,
        1,
        1,
        1,
        1,
        1,
        1,
        1,
        1,
        1,
        1,
        1,
        1,
        1,
        1,
        1,
        1,
        1,
        1,
        1,
        1,
        1,
        1,
        1,
        1,
        1,
        1,
        1,
        1,
        1,
        1,
        1,
        1,
        1,
        1,
        1,
        1,
        1,
        1,
        1,
        1,
        1,
        1,
        1,
        1,
        1,
        1,
        1,
        1,
        1,
        1,
        1,
        1,
        1,
        1,
        1,
        1,
        1,
        1,
        1,
        1,
        1,
        1,
        1,
        1,
        1,
        1,
        1,
        1,
        1,
        1,
        1,
        1,
        1,
        1,
        1,
        1,
        1,
        1
    ],
    "V": [
        1,
        1,
        2,
        3,
        4,
        5,
        6,
        7,
        8,
        9,
        10,
        11,
        12,
        13,
        14,
        15,
        16,
        17,
        18,
        19,
        20,
        21,
        22,
        23,
        24,
        25,
        26,
        27,
        28,
        29,
        30,
        31,
        32,
        33,
        34,
        35,
        36,
        37,
        38,
        39,
        40,
        41,
        42,
        43,
        44,
        45,
        46,
        47,
        48,
        49,
        50,
        51,
        52,
        53,
        54,
        55,
        56,
        57,
        58,
        59,
        60,
        61,
        62,
        63,
        64,
        65,
        66,
        67,
        68,
        69,
        70,
        71,
        72,
        73,
        74,
        75,
        76,
        77,
        78,
        79,
        80,
        81,
        82,
        83,
        84,
        85,
        86,
        87,
        88,
        89,
        90,
        91,
        92,
        93,
        94,
        95,
        96,
        97,
        98,
        99,
        100,
        101,
        102,
        103,
        104,
        105,
        106,
        107,
        108,
        109,
        110,
        111,
        112,
        113,
        114,
        115,
        116,
        117,
        118,
        119,
        120,
        121,
        122,
        123,
        124,
        125,
        126,
        127,
        128,
        129,
        130,
        131,
        132,
        133,
        134,
        135,
        136,
        137,
        138,
        139,
        140,
        141,
        142,
        143,
        144,
        145,
        146,
        147,
        148,
        149,
        150,
        151,
        152,
        153,
        154,
        155,
        156,
        157,
        158,
        159,
        160,
        161,
        162,
        163,
        164,
        165,
        166,
        167,
        168,
        169,
        170,
        171,
        172,
        173,
        174,
        175,
        176,
        177,
        178,
        179,
        180,
        181,
        182,
        183,
        184,
        185,
        186,
        187,
        188,
        189,
        190,
        191,
        192,
        193,
        194,
        195,
        196,
        197,
        198,
        199,
        200,
        201,
        202,
        203,
        204,
        205,
        206,
        207,
        208,
        209,
        210,
        211,
        212,
        213,
        214,
        215,
        216,
        217,
        218,
        219,
        220,
        221,
        222,
        223,
        224,
        225,
        226,
        227,
        228,
        229,
        230,
        231,
        232,
        233,
        234
    ],
    "feat": [
        [
            0,
            0,
            0,
            1,
            0.0,
            0.00851063829787234,
            0.0,
            1.0,
            -2.0
        ],
        [
            0,
            1,
            0,
            0,
            0.00851063829787234,
            0.9914893617021276,
            1.0,
            0.5,
            0.9999999999999996
        ],
        [
            0,
            0,
            0,
            1,
            0.00425531914893617,
            0.0,
            0.5,
            0.0,
            0.0011087898468123368
        ],
        [
            0,
            0,
            0,
            1,
            0.00425531914893617,
            0.0,
            0.5,
            0.0,
            0.00536687476560572
        ],
        [
            0,
            0,
            0,
            1,
            0.00425531914893617,
            0.0,
            0.5,
            0.0,
            0.007294294030898169
        ],
        [
            0,
            0,
            0,
            1,
            0.00425531914893617,
            0.0,
            0.5,
            0.0,
            0.0074153677949124405
        ],
        [
            0,
            0,
            0,
            1,
            0.00425531914893617,
            0.0,
            0.5,
            0.0,
            0.00769721333229928
        ],
        [
            0,
            0,
            0,
            1,
            0.00425531914893617,
            0.0,
            0.5,
            0.0,
            0.0033306560991231407
        ],
        [
            0,
            0,
            0,
            1,
            0.00425531914893617,
            0.0,
            0.5,
            0.0,
            0.0029180446991666433
        ],
        [
            0,
            0,
            0,
            1,
            0.00425531914893617,
            0.0,
            0.5,
            0.0,
            0.0023205259624722975
        ],
        [
            0,
            0,
            0,
            1,
            0.00425531914893617,
            0.0,
            0.5,
            0.0,
            0.0017763395904752666
        ],
        [
            0,
            0,
            0,
            1,
            0.00425531914893617,
            0.0,
            0.5,
            0.0,
            0.0024338185034900595
        ],
        [
            0,
            0,
            0,
            1,
            0.00425531914893617,
            0.0,
            0.5,
            0.0,
            0.004448156784068738
        ],
        [
            0,
            0,
            0,
            1,
            0.00425531914893617,
            0.0,
            0.5,
            0.0,
            0.005460456022705333
        ],
        [
            0,
            0,
            0,
            1,
            0.00425531914893617,
            0.0,
            0.5,
            0.0,
            0.0044763378947883965
        ],
        [
            0,
            0,
            0,
            1,
            0.00425531914893617,
            0.0,
            0.5,
            0.0,
            0.0026673068386707157
        ],
        [
            0,
            0,
            0,
            1,
            0.00425531914893617,
            0.0,
            0.5,
            0.0,
            0.003882554833736181
        ],
        [
            0,
            0,
            0,
            1,
            0.00425531914893617,
            0.0,
            0.5,
            0.0,
            0.001629821915866215
        ],
        [
            0,
            0,
            0,
            1,
            0.00425531914893617,
            0.0,
            0.5,
            0.0,
            0.007225623016444462
        ],
        [
            0,
            0,
            0,
            1,
            0.00425531914893617,
            0.0,
            0.5,
            0.0,
            0.00267908196373623
        ],
        [
            0,
            0,
            0,
            1,
            0.00425531914893617,
            0.0,
            0.5,
            0.0,
            0.003654454823329656
        ],
        [
            0,
            0,
            0,
            1,
            0.00425531914893617,
            0.0,
            0.5,
            0.0,
            0.005049979294544338
        ],
        [
            0,
            0,
            0,
            1,
            0.00425531914893617,
            0.0,
            0.5,
            0.0,
            0.005604374217950507
        ],
        [
            0,
            0,
            0,
            1,
            0.00425531914893617,
            0.0,
            0.5,
            0.0,
            0.006206093437855357
        ],
        [
            0,
            0,
            0,
            1,
            0.00425531914893617,
            0.0,
            0.5,
            0.0,
            0.0017506374534536106
        ],
        [
            0,
            0,
            0,
            1,
            0.00425531914893617,
            0.0,
            0.5,
            0.0,
            0.0016095941790943155
        ],
        [
            0,
            0,
            0,
            1,
            0.00425531914893617,
            0.0,
            0.5,
            0.0,
            0.0036599636537696626
        ],
        [
            0,
            0,
            0,
            1,
            0.00425531914893617,
            0.0,
            0.5,
            0.0,
            0.0017176533311940708
        ],
        [
            0,
            0,
            0,
            1,
            0.00425531914893617,
            0.0,
            0.5,
            0.0,
            0.007185804501420289
        ],
        [
            0,
            0,
            0,
            1,
            0.00425531914893617,
            0.0,
            0.5,
            0.0,
            0.007318980477307449
        ],
        [
            0,
            0,
            0,
            1,
            0.00425531914893617,
            0.0,
            0.5,
            0.0,
            0.006613901826271974
        ],
        [
            0,
            0,
            0,
            1,
            0.00425531914893617,
            0.0,
            0.5,
            0.0,
            0.0056566908920354445
        ],
        [
            0,
            0,
            0,
            1,
            0.00425531914893617,
            0.0,
            0.5,
            0.0,
            0.0018938670448937834
        ],
        [
            0,
            0,
            0,
            1,
            0.00425531914893617,
            0.0,
            0.5,
            0.0,
            0.005300545004089016
        ],
        [
            0,
            0,
            0,
            1,
            0.00425531914893617,
            0.0,
            0.5,
            0.0,
            0.005994519918768852
        ],
        [
            0,
            0,
            0,
            1,
            0.00425531914893617,
            0.0,
            0.5,
            0.0,
            0.0043660235652272636
        ],
        [
            0,
            0,
            0,
            1,
            0.00425531914893617,
            0.0,
            0.5,
            0.0,
            0.0019096188569331773
        ],
        [
            0,
            0,
            0,
            1,
            0.00425531914893617,
            0.0,
            0.5,
            0.0,
            0.0020802032345270077
        ],
        [
            0,
            0,
            0,
            1,
            0.00425531914893617,
            0.0,
            0.5,
            0.0,
            0.007128374944083219
        ],
        [
            0,
            0,
            0,
            1,
            0.00425531914893617,
            0.0,
            0.5,
            0.0,
            0.0019334961938715812
        ],
        [
            0,
            0,
            0,
            1,
            0.00425531914893617,
            0.0,
            0.5,
            0.0,
            0.00516742067348723
        ],
        [
            0,
            0,
            0,
            1,
            0.00425531914893617,
            0.0,
            0.5,
            0.0,
            0.0017081850288753093
        ],
        [
            0,
            0,
            0,
            1,
            0.00425531914893617,
            0.0,
            0.5,
            0.0,
            0.005061530623373227
        ],
        [
            0,
            0,
            0,
            1,
            0.00425531914893617,
            0.0,
            0.5,
            0.0,
            0.001206072349363829
        ],
        [
            0,
            0,
            0,
            1,
            0.00425531914893617,
            0.0,
            0.5,
            0.0,
            0.0067000289471824525
        ],
        [
            0,
            0,
            0,
            1,
            0.00425531914893617,
            0.0,
            0.5,
            0.0,
            0.0018030402030141735
        ],
        [
            0,
            0,
            0,
            1,
            0.00425531914893617,
            0.0,
            0.5,
            0.0,
            0.006579557711497558
        ],
        [
            0,
            0,
            0,
            1,
            0.00425531914893617,
            0.0,
            0.5,
            0.0,
            0.003254066140911923
        ],
        [
            0,
            0,
            0,
            1,
            0.00425531914893617,
            0.0,
            0.5,
            0.0,
            0.0009429396203778868
        ],
        [
            0,
            0,
            0,
            1,
            0.00425531914893617,
            0.0,
            0.5,
            0.0,
            0.0028029617882558795
        ],
        [
            0,
            0,
            0,
            1,
            0.00425531914893617,
            0.0,
            0.5,
            0.0,
            0.003801557811172958
        ],
        [
            0,
            0,
            0,
            1,
            0.00425531914893617,
            0.0,
            0.5,
            0.0,
            0.005902952827798867
        ],
        [
            0,
            0,
            0,
            1,
            0.00425531914893617,
            0.0,
            0.5,
            0.0,
            0.004375750093972901
        ],
        [
            0,
            0,
            0,
            1,
            0.00425531914893617,
            0.0,
            0.5,
            0.0,
            0.0027957142332082456
        ],
        [
            0,
            0,
            0,
            1,
            0.00425531914893617,
            0.0,
            0.5,
            0.0,
            0.0019199306989130648
        ],
        [
            0,
            0,
            0,
            1,
            0.00425531914893617,
            0.0,
            0.5,
            0.0,
            0.0036557115252737822
        ],
        [
            0,
            0,
            0,
            1,
            0.00425531914893617,
            0.0,
            0.5,
            0.0,
            0.0055626276122723315
        ],
        [
            0,
            0,
            0,
            1,
            0.00425531914893617,
            0.0,
            0.5,
            0.0,
            0.0012907361871886812
        ],
        [
            0,
            0,
            0,
            1,
            0.00425531914893617,
            0.0,
            0.5,
            0.0,
            0.005598538300703125
        ],
        [
            0,
            0,
            0,
            1,
            0.00425531914893617,
            0.0,
            0.5,
            0.0,
            0.0060371961395837784
        ],
        [
            0,
            0,
            0,
            1,
            0.00425531914893617,
            0.0,
            0.5,
            0.0,
            0.0055144942063027735
        ],
        [
            0,
            0,
            0,
            1,
            0.00425531914893617,
            0.0,
            0.5,
            0.0,
            0.0035465850372762755
        ],
        [
            0,
            0,
            0,
            1,
            0.00425531914893617,
            0.0,
            0.5,
            0.0,
            0.00482762912590957
        ],
        [
            0,
            0,
            0,
            1,
            0.00425531914893617,
            0.0,
            0.5,
            0.0,
            0.004936635108241202
        ],
        [
            0,
            0,
            0,
            1,
            0.00425531914893617,
            0.0,
            0.5,
            0.0,
            0.0026186914100376573
        ],
        [
            0,
            0,
            0,
            1,
            0.00425531914893617,
            0.0,
            0.5,
            0.0,
            0.007662077323149112
        ],
        [
            0,
            0,
            0,
            1,
            0.00425531914893617,
            0.0,
            0.5,
            0.0,
            0.006736559379037747
        ],
        [
            0,
            0,
            0,
            1,
            0.00425531914893617,
            0.0,
            0.5,
            0.0,
            0.005759051847648819
        ],
        [
            0,
            0,
            0,
            1,
            0.00425531914893617,
            0.0,
            0.5,
            0.0,
            0.00542461419465504
        ],
        [
            0,
            0,
            0,
            1,
            0.00425531914893617,
            0.0,
            0.5,
            0.0,
            0.0046177599012404424
        ],
        [
            0,
            0,
            0,
            1,
            0.00425531914893617,
            0.0,
            0.5,
            0.0,
            0.003658844672586536
        ],
        [
            0,
            0,
            0,
            1,
            0.00425531914893617,
            0.0,
            0.5,
            0.0,
            0.002725648796049411
        ],
        [
            0,
            0,
            0,
            1,
            0.00425531914893617,
            0.0,
            0.5,
            0.0,
            0.002278486700176997
        ],
        [
            0,
            0,
            0,
            1,
            0.00425531914893617,
            0.0,
            0.5,
            0.0,
            0.0026841087715127362
        ],
        [
            0,
            0,
            0,
            1,
            0.00425531914893617,
            0.0,
            0.5,
            0.0,
            0.007509499935056052
        ],
        [
            0,
            0,
            0,
            1,
            0.00425531914893617,
            0.0,
            0.5,
            0.0,
            0.003911063031263215
        ],
        [
            0,
            0,
            0,
            1,
            0.00425531914893617,
            0.0,
            0.5,
            0.0,
            0.006600766708691583
        ],
        [
            0,
            0,
            0,
            1,
            0.00425531914893617,
            0.0,
            0.5,
            0.0,
            0.0016492061129769883
        ],
        [
            0,
            0,
            0,
            1,
            0.00425531914893617,
            0.0,
            0.5,
            0.0,
            0.004058424245533393
        ],
        [
            0,
            0,
            0,
            1,
            0.00425531914893617,
            0.0,
            0.5,
            0.0,
            0.006095847968674724
        ],
        [
            0,
            0,
            0,
            1,
            0.00425531914893617,
            0.0,
            0.5,
            0.0,
            0.0065215772711164875
        ],
        [
            0,
            0,
            0,
            1,
            0.00425531914893617,
            0.0,
            0.5,
            0.0,
            0.004723856532495945
        ],
        [
            0,
            0,
            0,
            1,
            0.00425531914893617,
            0.0,
            0.5,
            0.0,
            0.004141452649321368
        ],
        [
            0,
            0,
            0,
            1,
            0.00425531914893617,
            0.0,
            0.5,
            0.0,
            0.0033495927037606632
        ],
        [
            0,
            0,
            0,
            1,
            0.00425531914893617,
            0.0,
            0.5,
            0.0,
            0.005629645977594037
        ],
        [
            0,
            0,
            0,
            1,
            0.00425531914893617,
            0.0,
            0.5,
            0.0,
            0.00598899387323372
        ],
        [
            0,
            0,
            0,
            1,
            0.00425531914893617,
            0.0,
            0.5,
            0.0,
            0.0065731192659208
        ],
        [
            0,
            0,
            0,
            1,
            0.00425531914893617,
            0.0,
            0.5,
            0.0,
            0.004961992943360357
        ],
        [
            0,
            0,
            0,
            1,
            0.00425531914893617,
            0.0,
            0.5,
            0.0,
            0.00391052936331434
        ],
        [
            0,
            0,
            0,
            1,
            0.00425531914893617,
            0.0,
            0.5,
            0.0,
            0.0058314241075544055
        ],
        [
            0,
            0,
            0,
            1,
            0.00425531914893617,
            0.0,
            0.5,
            0.0,
            0.006811617193782837
        ],
        [
            0,
            0,
            0,
            1,
            0.00425531914893617,
            0.0,
            0.5,
            0.0,
            0.002784214549664732
        ],
        [
            0,
            0,
            0,
            1,
            0.00425531914893617,
            0.0,
            0.5,
            0.0,
            0.001202732620909575
        ],
        [
            0,
            0,
            0,
            1,
            0.00425531914893617,
            0.0,
            0.5,
            0.0,
            0.005806995887572001
        ],
        [
            0,
            0,
            0,
            1,
            0.00425531914893617,
            0.0,
            0.5,
            0.0,
            0.0021643850496883593
        ],
        [
            0,
            0,
            0,
            1,
            0.00425531914893617,
            0.0,
            0.5,
            0.0,
            0.005787267388558727
        ],
        [
            0,
            0,
            0,
            1,
            0.00425531914893617,
            0.0,
            0.5,
            0.0,
            0.0047503505638933526
        ],
        [
            0,
            0,
            0,
            1,
            0.00425531914893617,
            0.0,
            0.5,
            0.0,
            0.004875091143169252
        ],
        [
            0,
            0,
            0,
            1,
            0.00425531914893617,
            0.0,
            0.5,
            0.0,
            0.006433367123695881
        ],
        [
            0,
            0,
            0,
            1,
            0.00425531914893617,
            0.0,
            0.5,
            0.0,
            0.003911476193546216
        ],
        [
            0,
            0,
            0,
            1,
            0.00425531914893617,
            0.0,
            0.5,
            0.0,
            0.005835125353006285
        ],
        [
            0,
            0,
            0,
            1,
            0.00425531914893617,
            0.0,
            0.5,
            0.0,
            0.004849475081623222
        ],
        [
            0,
            0,
            0,
            1,
            0.00425531914893617,
            0.0,
            0.5,
            0.0,
            0.007066297311062395
        ],
        [
            0,
            0,
            0,
            1,
            0.00425531914893617,
            0.0,
            0.5,
            0.0,
            0.00606367295588606
        ],
        [
            0,
            0,
            0,
            1,
            0.00425531914893617,
            0.0,
            0.5,
            0.0,
            0.0010608113766989039
        ],
        [
            0,
            0,
            0,
            1,
            0.00425531914893617,
            0.0,
            0.5,
            0.0,
            0.0012742957713442863
        ],
        [
            0,
            0,
            0,
            1,
            0.00425531914893617,
            0.0,
            0.5,
            0.0,
            0.0012941964213088104
        ],
        [
            0,
            0,
            0,
            1,
            0.00425531914893617,
            0.0,
            0.5,
            0.0,
            0.0038284477897582406
        ],
        [
            0,
            0,
            0,
            1,
            0.00425531914893617,
            0.0,
            0.5,
            0.0,
            0.004903203393508412
        ],
        [
            0,
            0,
            0,
            1,
            0.00425531914893617,
            0.0,
            0.5,
            0.0,
            0.005583543952849232
        ],
        [
            0,
            0,
            0,
            1,
            0.00425531914893617,
            0.0,
            0.5,
            0.0,
            0.007417863983705568
        ],
        [
            0,
            0,
            0,
            1,
            0.00425531914893617,
            0.0,
            0.5,
            0.0,
            0.0012080520853032064
        ],
        [
            0,
            0,
            0,
            1,
            0.00425531914893617,
            0.0,
            0.5,
            0.0,
            0.007421272572540322
        ],
        [
            0,
            0,
            0,
            1,
            0.00425531914893617,
            0.0,
            0.5,
            0.0,
            0.004759698360546238
        ],
        [
            0,
            0,
            0,
            1,
            0.00425531914893617,
            0.0,
            0.5,
            0.0,
            0.0055394216640438036
        ],
        [
            0,
            0,
            0,
            1,
            0.00425531914893617,
            0.0,
            0.5,
            0.0,
            0.007301214499138428
        ],
        [
            0,
            0,
            0,
            1,
            0.00425531914893617,
            0.0,
            0.5,
            0.0,
            0.004955468422307974
        ],
        [
            0,
            0,
            0,
            1,
            0.00425531914893617,
            0.0,
            0.5,
            0.0,
            0.004257224164037132
        ],
        [
            0,
            0,
            0,
            1,
            0.00425531914893617,
            0.0,
            0.5,
            0.0,
            0.0032043833763811132
        ],
        [
            0,
            0,
            0,
            1,
            0.00425531914893617,
            0.0,
            0.5,
            0.0,
            0.003563765702211047
        ],
        [
            0,
            0,
            0,
            1,
            0.00425531914893617,
            0.0,
            0.5,
            0.0,
            0.0018871015125096501
        ],
        [
            0,
            0,
            0,
            1,
            0.00425531914893617,
            0.0,
            0.5,
            0.0,
            0.001001109426805332
        ],
        [
            0,
            0,
            0,
            1,
            0.00425531914893617,
            0.0,
            0.5,
            0.0,
            0.002548161165310447
        ],
        [
            0,
            0,
            0,
            1,
            0.00425531914893617,
            0.0,
            0.5,
            0.0,
            0.007390491982456785
        ],
        [
            0,
            0,
            0,
            1,
            0.00425531914893617,
            0.0,
            0.5,
            0.0,
            0.007288372038175162
        ],
        [
            0,
            0,
            0,
            1,
            0.00425531914893617,
            0.0,
            0.5,
            0.0,
            0.005742146624236048
        ],
        [
            0,
            0,
            0,
            1,
            0.00425531914893617,
            0.0,
            0.5,
            0.0,
            0.0034218961032857504
        ],
        [
            0,
            0,
            0,
            1,
            0.00425531914893617,
            0.0,
            0.5,
            0.0,
            0.0030599831584724392
        ],
        [
            0,
            0,
            0,
            1,
            0.00425531914893617,
            0.0,
            0.5,
            0.0,
            0.0011353527385902437
        ],
        [
            0,
            0,
            0,
            1,
            0.00425531914893617,
            0.0,
            0.5,
            0.0,
            0.00585962243336919
        ],
        [
            0,
            0,
            0,
            1,
            0.00425531914893617,
            0.0,
            0.5,
            0.0,
            0.005594423892968245
        ],
        [
            0,
            0,
            0,
            1,
            0.00425531914893617,
            0.0,
            0.5,
            0.0,
            0.0014569995759061314
        ],
        [
            0,
            0,
            0,
            1,
            0.00425531914893617,
            0.0,
            0.5,
            0.0,
            0.005019164274270551
        ],
        [
            0,
            0,
            0,
            1,
            0.00425531914893617,
            0.0,
            0.5,
            0.0,
            0.00375753881293828
        ],
        [
            0,
            0,
            0,
            1,
            0.00425531914893617,
            0.0,
            0.5,
            0.0,
            0.0028321413744927895
        ],
        [
            0,
            0,
            0,
            1,
            0.00425531914893617,
            0.0,
            0.5,
            0.0,
            0.006716417717741473
        ],
        [
            0,
            0,
            0,
            1,
            0.00425531914893617,
            0.0,
            0.5,
            0.0,
            0.001048261572352764
        ],
        [
            0,
            0,
            0,
            1,
            0.00425531914893617,
            0.0,
            0.5,
            0.0,
            0.0016343839160743454
        ],
        [
            0,
            0,
            0,
            1,
            0.00425531914893617,
            0.0,
            0.5,
            0.0,
            0.004251284956219001
        ],
        [
            0,
            0,
            0,
            1,
            0.00425531914893617,
            0.0,
            0.5,
            0.0,
            0.0040490592337853815
        ],
        [
            0,
            0,
            0,
            1,
            0.00425531914893617,
            0.0,
            0.5,
            0.0,
            0.003557551052870914
        ],
        [
            0,
            0,
            0,
            1,
            0.00425531914893617,
            0.0,
            0.5,
            0.0,
            0.0028253586270135314
        ],
        [
            0,
            0,
            0,
            1,
            0.00425531914893617,
            0.0,
            0.5,
            0.0,
            0.0033914598151047136
        ],
        [
            0,
            0,
            0,
            1,
            0.00425531914893617,
            0.0,
            0.5,
            0.0,
            0.004019397624884971
        ],
        [
            0,
            0,
            0,
            1,
            0.00425531914893617,
            0.0,
            0.5,
            0.0,
            0.0028683102893504583
        ],
        [
            0,
            0,
            0,
            1,
            0.00425531914893617,
            0.0,
            0.5,
            0.0,
            0.007168090168536642
        ],
        [
            0,
            0,
            0,
            1,
            0.00425531914893617,
            0.0,
            0.5,
            0.0,
            0.0030494991655413014
        ],
        [
            0,
            0,
            0,
            1,
            0.00425531914893617,
            0.0,
            0.5,
            0.0,
            0.001651220279106616
        ],
        [
            0,
            0,
            0,
            1,
            0.00425531914893617,
            0.0,
            0.5,
            0.0,
            0.0038601235647882782
        ],
        [
            0,
            0,
            0,
            1,
            0.00425531914893617,
            0.0,
            0.5,
            0.0,
            0.002637369788248305
        ],
        [
            0,
            0,
            0,
            1,
            0.00425531914893617,
            0.0,
            0.5,
            0.0,
            0.006906455152826577
        ],
        [
            0,
            0,
            0,
            1,
            0.00425531914893617,
            0.0,
            0.5,
            0.0,
            0.0025367303421474333
        ],
        [
            0,
            0,
            0,
            1,
            0.00425531914893617,
            0.0,
            0.5,
            0.0,
            0.0034187113106876215
        ],
        [
            0,
            0,
            0,
            1,
            0.00425531914893617,
            0.0,
            0.5,
            0.0,
            0.003921512594004102
        ],
        [
            0,
            0,
            0,
            1,
            0.00425531914893617,
            0.0,
            0.5,
            0.0,
            0.005980024808673584
        ],
        [
            0,
            0,
            0,
            1,
            0.00425531914893617,
            0.0,
            0.5,
            0.0,
            0.00606301878227131
        ],
        [
            0,
            0,
            0,
            1,
            0.00425531914893617,
            0.0,
            0.5,
            0.0,
            0.004521871821394077
        ],
        [
            0,
            0,
            0,
            1,
            0.00425531914893617,
            0.0,
            0.5,
            0.0,
            0.003393405120853841
        ],
        [
            0,
            0,
            0,
            1,
            0.00425531914893617,
            0.0,
            0.5,
            0.0,
            0.006637297140546877
        ],
        [
            0,
            0,
            0,
            1,
            0.00425531914893617,
            0.0,
            0.5,
            0.0,
            0.0028915506677692363
        ],
        [
            0,
            0,
            0,
            1,
            0.00425531914893617,
            0.0,
            0.5,
            0.0,
            0.0037005740631695866
        ],
        [
            0,
            0,
            0,
            1,
            0.00425531914893617,
            0.0,
            0.5,
            0.0,
            0.0026443591168690632
        ],
        [
            0,
            0,
            0,
            1,
            0.00425531914893617,
            0.0,
            0.5,
            0.0,
            0.00668116120292543
        ],
        [
            0,
            0,
            0,
            1,
            0.00425531914893617,
            0.0,
            0.5,
            0.0,
            0.004372186569282021
        ],
        [
            0,
            0,
            0,
            1,
            0.00425531914893617,
            0.0,
            0.5,
            0.0,
            0.0011621049964145262
        ],
        [
            0,
            0,
            0,
            1,
            0.00425531914893617,
            0.0,
            0.5,
            0.0,
            0.005411943884643024
        ],
        [
            0,
            0,
            0,
            1,
            0.00425531914893617,
            0.0,
            0.5,
            0.0,
            0.002752073967066318
        ],
        [
            0,
            0,
            0,
            1,
            0.00425531914893617,
            0.0,
            0.5,
            0.0,
            0.006794884121321317
        ],
        [
            0,
            0,
            0,
            1,
            0.00425531914893617,
            0.0,
            0.5,
            0.0,
            0.0031630155027956883
        ],
        [
            0,
            0,
            0,
            1,
            0.00425531914893617,
            0.0,
            0.5,
            0.0,
            0.0018950376713622848
        ],
        [
            0,
            0,
            0,
            1,
            0.00425531914893617,
            0.0,
            0.5,
            0.0,
            0.004518394372178823
        ],
        [
            0,
            0,
            0,
            1,
            0.00425531914893617,
            0.0,
            0.5,
            0.0,
            0.004135220784886111
        ],
        [
            0,
            0,
            0,
            1,
            0.00425531914893617,
            0.0,
            0.5,
            0.0,
            0.002030296673759573
        ],
        [
            0,
            0,
            0,
            1,
            0.00425531914893617,
            0.0,
            0.5,
            0.0,
            0.0059328382329359025
        ],
        [
            0,
            0,
            0,
            1,
            0.00425531914893617,
            0.0,
            0.5,
            0.0,
            0.0016284791384464634
        ],
        [
            0,
            0,
            0,
            1,
            0.00425531914893617,
            0.0,
            0.5,
            0.0,
            0.0010496904252481406
        ],
        [
            0,
            0,
            0,
            1,
            0.00425531914893617,
            0.0,
            0.5,
            0.0,
            0.004978416144109627
        ],
        [
            0,
            0,
            0,
            1,
            0.00425531914893617,
            0.0,
            0.5,
            0.0,
            0.005166284477208978
        ],
        [
            0,
            0,
            0,
            1,
            0.00425531914893617,
            0.0,
            0.5,
            0.0,
            0.00544155384825806
        ],
        [
            0,
            0,
            0,
            1,
            0.00425531914893617,
            0.0,
            0.5,
            0.0,
            0.004184163300326544
        ],
        [
            0,
            0,
            0,
            1,
            0.00425531914893617,
            0.0,
            0.5,
            0.0,
            0.007712706917911798
        ],
        [
            0,
            0,
            0,
            1,
            0.00425531914893617,
            0.0,
            0.5,
            0.0,
            0.006962163200651144
        ],
        [
            0,
            0,
            0,
            1,
            0.00425531914893617,
            0.0,
            0.5,
            0.0,
            0.006049195060885918
        ],
        [
            0,
            0,
            0,
            1,
            0.00425531914893617,
            0.0,
            0.5,
            0.0,
            0.0026712663105494705
        ],
        [
            0,
            0,
            0,
            1,
            0.00425531914893617,
            0.0,
            0.5,
            0.0,
            0.001180439072722673
        ],
        [
            0,
            0,
            0,
            1,
            0.00425531914893617,
            0.0,
            0.5,
            0.0,
            0.00719095181486267
        ],
        [
            0,
            0,
            0,
            1,
            0.00425531914893617,
            0.0,
            0.5,
            0.0,
            0.0017142103121690667
        ],
        [
            0,
            0,
            0,
            1,
            0.00425531914893617,
            0.0,
            0.5,
            0.0,
            0.0073804727970940235
        ],
        [
            0,
            0,
            0,
            1,
            0.00425531914893617,
            0.0,
            0.5,
            0.0,
            0.006242916526327777
        ],
        [
            0,
            0,
            0,
            1,
            0.00425531914893617,
            0.0,
            0.5,
            0.0,
            0.006174228296778944
        ],
        [
            0,
            0,
            0,
            1,
            0.00425531914893617,
            0.0,
            0.5,
            0.0,
            0.005873687166086331
        ],
        [
            0,
            0,
            0,
            1,
            0.00425531914893617,
            0.0,
            0.5,
            0.0,
            0.0038111638342527196
        ],
        [
            0,
            0,
            0,
            1,
            0.00425531914893617,
            0.0,
            0.5,
            0.0,
            0.003463866505200551
        ],
        [
            0,
            0,
            0,
            1,
            0.00425531914893617,
            0.0,
            0.5,
            0.0,
            0.005068141219901235
        ],
        [
            0,
            0,
            0,
            1,
            0.00425531914893617,
            0.0,
            0.5,
            0.0,
            0.005821508212762393
        ],
        [
            0,
            0,
            0,
            1,
            0.00425531914893617,
            0.0,
            0.5,
            0.0,
            0.004319577238579958
        ],
        [
            0,
            0,
            0,
            1,
            0.00425531914893617,
            0.0,
            0.5,
            0.0,
            0.00444161504792123
        ],
        [
            0,
            0,
            0,
            1,
            0.00425531914893617,
            0.0,
            0.5,
            0.0,
            0.006491709081074577
        ],
        [
            0,
            0,
            0,
            1,
            0.00425531914893617,
            0.0,
            0.5,
            0.0,
            0.00398513958558618
        ],
        [
            0,
            0,
            0,
            1,
            0.00425531914893617,
            0.0,
            0.5,
            0.0,
            0.0029866468532398507
        ],
        [
            0,
            0,
            0,
            1,
            0.00425531914893617,
            0.0,
            0.5,
            0.0,
            0.004788172127883023
        ],
        [
            0,
            0,
            0,
            1,
            0.00425531914893617,
            0.0,
            0.5,
            0.0,
            0.003718340041338608
        ],
        [
            0,
            0,
            0,
            1,
            0.00425531914893617,
            0.0,
            0.5,
            0.0,
            0.0011877210579605568
        ],
        [
            0,
            0,
            0,
            1,
            0.00425531914893617,
            0.0,
            0.5,
            0.0,
            0.005888027340325474
        ],
        [
            0,
            0,
            0,
            1,
            0.00425531914893617,
            0.0,
            0.5,
            0.0,
            0.003966392346995032
        ],
        [
            0,
            0,
            0,
            1,
            0.00425531914893617,
            0.0,
            0.5,
            0.0,
            0.001157198694303895
        ],
        [
            0,
            0,
            0,
            1,
            0.00425531914893617,
            0.0,
            0.5,
            0.0,
            0.006415325704004859
        ],
        [
            0,
            0,
            0,
            1,
            0.00425531914893617,
            0.0,
            0.5,
            0.0,
            0.005739288918445294
        ],
        [
            0,
            0,
            0,
            1,
            0.00425531914893617,
            0.0,
            0.5,
            0.0,
            0.0008944963426960784
        ],
        [
            0,
            0,
            0,
            1,
            0.00425531914893617,
            0.0,
            0.5,
            0.0,
            0.003526099074077501
        ],
        [
            0,
            0,
            0,
            1,
            0.00425531914893617,
            0.0,
            0.5,
            0.0,
            0.006242296782903276
        ],
        [
            0,
            0,
            0,
            1,
            0.00425531914893617,
            0.0,
            0.5,
            0.0,
            0.00442491640564996
        ],
        [
            0,
            0,
            0,
            1,
            0.00425531914893617,
            0.0,
            0.5,
            0.0,
            0.007455702762790362
        ],
        [
            0,
            0,
            0,
            1,
            0.00425531914893617,
            0.0,
            0.5,
            0.0,
            0.002581833891374988
        ],
        [
            0,
            0,
            0,
            1,
            0.00425531914893617,
            0.0,
            0.5,
            0.0,
            0.0046326853887138355
        ],
        [
            0,
            0,
            0,
            1,
            0.00425531914893617,
            0.0,
            0.5,
            0.0,
            0.003962398444926028
        ],
        [
            0,
            0,
            0,
            1,
            0.00425531914893617,
            0.0,
            0.5,
            0.0,
            0.0042797587235557846
        ],
        [
            0,
            0,
            0,
            1,
            0.00425531914893617,
            0.0,
            0.5,
            0.0,
            0.007500806312017919
        ],
        [
            0,
            0,
            0,
            1,
            0.00425531914893617,
            0.0,
            0.5,
            0.0,
            0.005653213442820191
        ],
        [
            0,
            0,
            0,
            1,
            0.00425531914893617,
            0.0,
            0.5,
            0.0,
            0.0025939016730576274
        ],
        [
            0,
            0,
            0,
            1,
            0.00425531914893617,
            0.0,
            0.5,
            0.0,
            0.002685830281025238
        ],
        [
            0,
            0,
            0,
            1,
            0.00425531914893617,
            0.0,
            0.5,
            0.0,
            0.0015624420335468836
        ],
        [
            0,
            0,
            0,
            1,
            0.00425531914893617,
            0.0,
            0.5,
            0.0,
            0.0033256981517271345
        ],
        [
            0,
            0,
            0,
            1,
            0.00425531914893617,
            0.0,
            0.5,
            0.0,
            0.007358351399858371
        ],
        [
            0,
            0,
            0,
            1,
            0.00425531914893617,
            0.0,
            0.5,
            0.0,
            0.0032775475306624515
        ],
        [
            0,
            0,
            0,
            1,
            0.00425531914893617,
            0.0,
            0.5,
            0.0,
            0.002316600920783793
        ],
        [
            0,
            0,
            0,
            1,
            0.00425531914893617,
            0.0,
            0.5,
            0.0,
            0.00765928847773886
        ],
        [
            0,
            0,
            0,
            1,
            0.00425531914893617,
            0.0,
            0.5,
            0.0,
            0.006041327762413784
        ],
        [
            0,
            0,
            0,
            1,
            0.00425531914893617,
            0.0,
            0.5,
            0.0,
            0.002195234500152397
        ],
        [
            0,
            0,
            0,
            1,
            0.00425531914893617,
            0.0,
            0.5,
            0.0,
            0.005170071798136483
        ],
        [
            0,
            0,
            0,
            1,
            0.00425531914893617,
            0.0,
            0.5,
            0.0,
            0.0024272939824376764
        ],
        [
            0,
            0,
            0,
            1,
            0.00425531914893617,
            0.0,
            0.5,
            0.0,
            0.007602857395919041
        ],
        [
            0,
            0,
            0,
            1,
            0.00425531914893617,
            0.0,
            0.5,
            0.0,
            0.004928939960720318
        ],
        [
            0,
            0,
            0,
            1,
            0.00425531914893617,
            0.0,
            0.5,
            0.0,
            0.002779428753219976
        ],
        [
            0,
            0,
            0,
            1,
            0.00425531914893617,
            0.0,
            0.5,
            0.0,
            0.002587687023717495
        ]
    ],
    "nodeCount": 235,
    "edgeCount": 235,
    "tokenCount": 2,
    "nodes": [
        "0x911512e8c0fe8dd53261a12e02c35773d92b7b62",
        "0xa5025faba6e70b84f74e9b1113e5f7f4e7f4859f",
        "0x20214d8b06f1afa1ed8b2a883b72c6f0d3ba4ff1",
        "0x85ae4af6c22eccb981be8f8758966c093d9c5c02",
        "0x320d2540df25b2a30b89fe921ba96b18a9144659",
        "0x4906d172361df6a10a7123eda61f23a492bd73cb",
        "0xb95195f33b313ba920367284017825b566b84e31",
        "0x97caabedae195f65469f9a9cf6e9f0ab4941a78f",
        "0x9bd4f50d2dbc4533df066d8d0f4a5a91673c0e43",
        "0x8009d617fef9f41c807c463f01035b76382a4e55",
        "0x81e7f7935c20a90e0ed4ea0f8ef2b4c9ada48a47",
        "0xc01a5931e6357966fa7ddeb84fa741b0136fadbf",
        "0x0d5f25200fb3c2280369878df555bc77a1388364",
        "0xaf82d3379d85b0b58034b5a6ffd88fc1e2df5aad",
        "0x92469df1f2fa8b63018a59c85fb890f701c57acb",
        "0x3268eefd8970c5c62a0499011b41dd56d851d6d8",
        "0x633485d416eae478ef39e7df7f7ef66296eeee1a",
        "0x59d8bfc0cd21e5ecabf36113a634c92c975df1c9",
        "0xe1ebeaf9af14187c1346cf8faccbaf246e0df612",
        "0x06f2fcbd1c629c0243d1103139cd9c4af1ab8262",
        "0x28cd4221961226a3d2e5b3b945b0c7c7cfb4812c",
        "0x9ca80629d34f7693931f7b9a3d4c79f72857c208",
        "0xef0a2d40a7db04dcce4e8ab1841a69f366e60bbe",
        "0x69bc327e2aaa7983257fdb2e53efffab0af965ea",
        "0xd7e1410a01b0a7ede5e11cb0ee13facd9ce16160",
        "0x80423378a47abed234d3217cef0c16dd491f9c72",
        "0x73c3175f766c4137914a017e13cd13169380bddd",
        "0x1993c6fc11ed5919514d43a6d4d2346d22d2f626",
        "0xbc78aea94265c2c9cf6fb09d3f568af86b6c7876",
        "0x2624c033109c36e495e56dcbbb9f04ef20dc682e",
        "0x0a6d224ad7b34a85ea1a3278bf7c001513beaa04",
        "0xde61b2ffc392fb96e5ffc54f6a48fb60d479c14b",
        "0xb7bfc68277596912e45be472f65164cd2313c144",
        "0x583fdc4f5f8bc12eb16180f88df3dc00605d725e",
        "0x9d466488c0970b9e8b87e0afda6faac3908290bf",
        "0xed2dada5cd93cb45886901b3635ddc80fbc6b474",
        "0xae405c4e04a82bf82ac959508285e85fa17d90cf",
        "0xc1a4b7621fe69660c79ad13f584767edbfcbacfd",
        "0x67916dd45b6517626bc89517124728c8bc1e91d0",
        "0xbb2d4aec963c965d817086cf82ec4e40a1969758",
        "0x6d884e743fd2376c5fe974bdbc1614014687cc21",
        "0x36c7c7a4b11fef261a82cb78bfc0723f15081057",
        "0x15139f8887b8f49b07c3e7e097e4a596cad2f953",
        "0x19956aa250e446f6722077649ee8c159facf69e4",
        "0xb06295ee2e2ba8511c70ba515207a77193849203",
        "0x6a333b0ee8336140b84d7ea81aecbae60a75c13c",
        "0xa49733066a8cd1d089f3cdb7beafd98cbc0adbb4",
        "0xd5b92d4af7f0030b47e5f5eaad859aec7c9933fc",
        "0xf80b0376331212ef7f633ef7cbbdef916b958249",
        "0x07538367d8801b9156a51627ff21edd1ff49d2bf",
        "0xcafec0fa8c0098c8c9e05be521db774830bed14c",
        "0x4e13a23ba8df183bf8740076133384313321e435",
        "0x0217931dc85ea3022744b121a9c27b1237224788",
        "0xb08c6c59fffd6eed057169e3b43115f7604446f3",
        "0x54745c6a38b462b1e018023d67847d6a1e958847",
        "0x41ca13e3be52542ad691ef316011d6341e004652",
        "0xd7b85b0a27561e783597ca0a8f09f59ce00dedf1",
        "0xb8339072b4c813b5a7fc71f9b6ca5d2c658bd701",
        "0x4a04d5a6d0b4197ff2be54c2e2b3bf3a54c917b7",
        "0xf82d66c2dc0b7ca9e991647f760112883825c760",
        "0x98dd3df47fc4e641f58cdcdba45dc74e91219b5f",
        "0xc6303d9395dfcea6356612d8f00ce0fa8973fe87",
        "0xdb038ef7ba4fe963c80ca840cf115d8469fd642c",
        "0xc8dc6aed878e66d6a8523c5423d99994b6ffba81",
        "0xf96189d3a5cb50e374c7fc702bd93f5cf3c86373",
        "0xfa8cd8ce8613c9f40092a3cd617af6437ea13645",
        "0x46435e9fe1f4f0482ae6604b6eb002f1ce92810c",
        "0xf59107438a61f432b2f9784254f94b2174727cb4",
        "0xc08b98d3dd9363ecfc1d364f72e9441f1afa69f7",
        "0x213d11016a77090095efe3f88711f9a50ed563ec",
        "0xbd3d9528736e12ab1533d714f35de153a28b0b21",
        "0xffacb582858deabaa7b7bf232f338b8014673a18",
        "0x468bec77754274578b0d815174017a92e217563d",
        "0xd3b4737dc5159928a242fd756c9394c9ecce126a",
        "0x7b090a40f8d695621aa72e7889d8ea9662d93dda",
        "0x055358e5388a2bf2961db6ee54bdcc7bf3697147",
        "0xe7c4515682b2d66629fd62fb55cb0a9eb87275fa",
        "0x6379da0642154264c4186d81f41368a34684e488",
        "0xf0bd32e30e478b5cee6de8ea138c11a9fd075cb7",
        "0xaf761be77c9a9c4539fd9e0a57bec20843bb2eae",
        "0xcefc53c204517c27eaee863ba424a0e8e81e8d9a",
        "0xdad389d3fbbfa5652ec59ab8a61bdd2d7e102db8",
        "0x3cee2574b84b3cfeeb5d21366ad5e0ca248fc2ad",
        "0x481b18b42e300d0381362a722d6f049bcc1a5f50",
        "0x8ad3f5eb3b8ef763aee756431a44e88472b7bf91",
        "0x84ae76e10413c0b017f653bf899ecc8795659ab3",
        "0xce524c2362a414020cef96871af13df0f0348300",
        "0x7f3d3bb80d0ce17b61a121a9f8f277ac80edd343",
        "0x54a5df13776136c4a47dfffde3c9ce4dc7678630",
        "0x3010b12b61d252799686914a3e44b6a5b7de82fd",
        "0x9d14e94010175e3aef3364ebf0410200126281f0",
        "0x6b9355616aa56e39c4b5ec2c7b02924dc882d8c9",
        "0x69459ee45170c5cf55325134f52d78b724354b81",
        "0xa93f4c4071864d257d6b01754f6b6363826f5eee",
        "0x365eb3cdcbe055f7b9dda778dd0b7c32c72b8615",
        "0xc89bf45262c5be9c15ff0c0e99bc61d335050290",
        "0x318529e4d857d4411bd8fb4fa1d66f2c97133a04",
        "0xac35d0feaabe07ca45a1a2e9b338ca8c42ecac56",
        "0xf59a280964da34b0c73e4141af6eb3a00684ada4",
        "0xb36051f980584ce772e7e8b6c9d78a4fdfad9a56",
        "0x3865c1230cb36b4fff04c870633688273de15c8c",
        "0xd1708378c01c1dcdecbf80be5d7f83199d895cb7",
        "0x656e7e0bf183bc9f2724b79820ab4f5a6016a32b",
        "0x1fd2dadd67a833b1fe7351da3c8408d67283a41f",
        "0xb02316797f70a8dd7293a7154e22c8d963c2e71c",
        "0xad28caf3fcc23864ada1839e3eef3377154f8669",
        "0x4535a8800afafbdfd941733b1d1a1d2efa06e7e8",
        "0x7273bcd1e4854e2ee1b8709bbdcb19d7046b97c6",
        "0x14dfea232b59982ae669eb6319c01b75162912d1",
        "0x90d9221b30241b755063a84d3055674280bdf09b",
        "0xbe31ea2b2fa529460e299ee389662711508012b4",
        "0xbca169d3e78e87948891d6f703820a2e02b92fcc",
        "0x93f0dc175d177382ccc6ba05a7c1f011566efc9e",
        "0xcb85704244bead0c22b2e680fc60dc003df945f9",
        "0x1616e5984f64f8aa904e4fae592f9a2839ec8421",
        "0xcd950cd447f9bcc0e2ab06f66349f999b0cf7dc5",
        "0xc7a5a3549b32c0f5acb2dfd48e1176206cecb7ca",
        "0xb952a210f6e7e4d1e6b8ea5f5e3248f3ec07c99f",
        "0x5916e98c21e71aa77bbdc18dcd229c52a2dcfacb",
        "0x66cd59f7722f83a3e60f5a0c10b8c5c354040a25",
        "0x89b200c65667234921651bbdb682bb99fc3fb61a",
        "0xdecb3b5176e85c26a384ae5298d1db2eebd9b064",
        "0x1ce8271535e70f8b215ed3333187d466af7b3dd0",
        "0xff32dae4c13bd07faeb5bc2d350a17bd16ac940c",
        "0x265ff89cdb4b011e2c4c8428c38d03fad0c2b08d",
        "0x2fb6a58370c82f2003bbbe33fe7589109362b0ec",
        "0x49f792b0b73e1ef6019c00cd554a1e15df39b032",
        "0x2efe53fa01ba0b8e819c2a726ef119e83f34d6e8",
        "0x3a63baab366b2298ffdeb36ca8b27a9b0004c113",
        "0xd6e15c20e893979e0b191f73f2ab2e2572d5b1ea",
        "0x4aca1be009d0d296708f04a3509ab268d6efb6d0",
        "0x73e431b32b1e6dd47f335c657b8fde4aebb93dd9",
        "0x043b6aa34f81b407ed2bf82c0a46a9794c20b345",
        "0x4b56f32d21259c7f9b8e204d578f4e409f03b00e",
        "0xcd5ad2f8caed9bbb5c1136f9b3a5944266d2e38b",
        "0xdb0e943e4fc32ae48d9e2745c3fcc19fbac9924d",
        "0xb03ec17eddd6deeff0cfb65f31620bcfee3fc17b",
        "0xa5b59b8f37d9480ff629620a848a928b2236b123",
        "0x141d3d944c46e4506c2ae334eddb138234dae5fb",
        "0x8e55ab9588b3987cbc66499bcf0467b5983d2329",
        "0xbd34813dff925e8570d5210888192204de23b840",
        "0xccdb00ddac605280d4e2598cf689be5eff4d8ee4",
        "0xdbc238986816af6051674f620bc652b8c7bc22c8",
        "0x42cceb73f62a01fccd3fa7bdb283e49bf6305666",
        "0x36920d83b931ff1039341ab017b6e1c53523b75d",
        "0x3fac223aa228a99ae898d72d17a19d37d95942d9",
        "0xc12ac5d7ece39bc2c98ce27bb597a4e2949e1c5e",
        "0xde749d7a17bef623233ae89eb5d15061ddefb1ce",
        "0x007309eedb5d224ca0f7d8922baee38bf276d6b3",
        "0x59a8fbadea6c7d0c8056f13c6f805eabab36cb6e",
        "0xcebb943c2d01f6d8b46e68d3b0e7cada824a8af8",
        "0x4876a0b856bd981b403c20ae0c3210f19ccf80a7",
        "0x67e42df4bdf0e3b5981f3009d05469c735559fba",
        "0xae4f93d92f3daf7603d71307c29548e00b5b468f",
        "0x2bffaffea73d45968b6567a73f7a735d8f547e77",
        "0xc90224093d7653a9752daf469d966048da00388a",
        "0x08469dc5df3050ff47bfd958684ec4d493306d54",
        "0xd9c096bcd25587d77056c71f4f76a041e06e36d2",
        "0xa7b96be4c983a3a7578e63dd7d9f340fb3e7a85b",
        "0xd675bfc9339fc6be6a5ac5be0dc05636c6127922",
        "0xdd3813846d4f9083614a40901d15c40e70e8a854",
        "0x747640f5e72db7858ba066e314aa17fa294b1c1a",
        "0x1b4edf53ef58a29249c2f85259851f3876b17159",
        "0xc695e13c9d39866f68006bd873491cfca85f4de1",
        "0x0d0d1e61b549714602fc2043d7546eb316e99141",
        "0x111452b6ac62531f75cb3c58029b49c1e438ae0a",
        "0xc385367eca9274129d70488cd0acfc4c514b9fc6",
        "0xcaa7ad500304cbafe5f0957825c33d8bf2f23aba",
        "0xf6f4494b093de4018db6dcd15b4489c972bc4c8c",
        "0xd610b6f11572acedab370eab71cc2d32007073b1",
        "0xcc3d441ec259f4fc8438095f1a26b86574d3dbec",
        "0xbdccbc2fb72a47b907cda1bd62a3d59295654af4",
        "0x53ff77f93a43b4b50308a9a2cd796c6290889e38",
        "0x7de8092521b491b943e4d853b80fc772f0843f7c",
        "0xf897018b3e37bc59858bb9e059c5042b99dc14e5",
        "0x9bc6ea06620c5e3446264a7f0e62f40719d485f7",
        "0x80148237b494f1abc7f7414aba20746b9417bab9",
        "0xdf07230e18936efda1739dc2fba80c18d6c009a4",
        "0x5db23f1b36a09134fd8848afc882574ad67becec",
        "0x5b179ab4182c976e7ebe45280e81505b81f332d3",
        "0x01b92018fa87039e57519041fb2984a3e2f2f54d",
        "0x4e75f92aeaa029abde588ae3bc923caacfd542a5",
        "0xa9870d0e0bd625c8373e437144a2b0e51c7bd1eb",
        "0x3c5965177578d3bd9c685d8261e2aca050d3f547",
        "0x4700942d91a41d63354e73fd3d6abf2762177ade",
        "0xf433f1f61d62e434de559f92d660f038d9949cb9",
        "0x6e894572bcc32c7fe7e4b7bd0cbdd3df897b9eb0",
        "0x5e107f69e36d27ab617002291ee0d0e936133f70",
        "0xe0c20afa69ae35df0bd5377f7130ec469bf4c69d",
        "0x562c4cb49cd4757b6d66127961d91dc05aa20a9d",
        "0x70444d3f37224e7cb1f491b29dc6eb9748d44c43",
        "0xb79dbfa18616b042fd6d988d1e59973cca4775b4",
        "0x419d42d0bb7967b37ef35822c8cee22cd9eb38ce",
        "0xdca0d40d726bca1569bf4d949f0f925d9e5a5932",
        "0x599e4a4a23ee5dcfb25c9d1c3e0bf66dbeea754a",
        "0x18e1fcc31fe9a59d2c300c2dfa3163d374901edf",
        "0x65af14960dce17b6ea92feb3c87d2d92042d4e21",
        "0x0621d41d106bc6e21e6f7f642d33ff21da9ae61c",
        "0x9037fcf47dbb69f232fdd84c0ae25db697a94c1c",
        "0xd640186d945bdb0685bc6a6c41b1a054a0a8fec5",
        "0xdfe5fc0a4b0a74250b845af4a0a886779b095db7",
        "0xdc2d671a5c53e1a6aad2ae96ca1012cfe279abcb",
        "0x0121ffca2d4e2926ec758a3cc222ae8ff4ba8939",
        "0xc3ebb7a363f790ccfc491239f68d81cb12aeec48",
        "0xf6db943972ed4c2f45e3869290e17177d9048727",
        "0x14430b9b116f194848701a1e29ec21abb3e2849d",
        "0xc76cfcb31a1cdbff5f5aa9973261a437352f7b37",
        "0xbb99d8b991d9146567cf6ddff0618dd448c618e4",
        "0x89622f87801997397bc9487aaff7daa3ec98b99d",
        "0xc5f2fbcf626a0b4d08516a9e91b95f80d9b0e942",
        "0xdbacdfbb28a4e3d36b8448a33ced4f1c18f0d193",
        "0x960d919089dbb07b288b9299683786ba80d82b57",
        "0x5b1a4b940403e87ddf4759b3f364ed825bfa4555",
        "0xca29ff034c0b9d95962e43f013f3dbdb3d8112a6",
        "0x1fb8dd49c658220928f1e1e2b6ea5dd5b5cb9cf6",
        "0x8d0d40e8bd45987073f1983c66e565b31a4c365c",
        "0xaf385b8eff05b735488dbf5c2d0ec71f6a27e1e7",
        "0x41317f4d020bc9df6042ddafe3aaeb72f7f2cb79",
        "0x814cc08bc74ae92219c840590a8bfd5c188c16c7",
        "0x2d2844d9cbf6fb9bdfcf6f462deb0d39f86d6197",
        "0x103af1d296e2bbd7e1a0ef5a2f39e8661fb79afb",
        "0x7d9ad4b3e7f9c44fc121f5c37da1fbbd958e751b",
        "0x89f14f6234b7ca3e8a9208f838197a39f6495cb1",
        "0xf6c2862f1e732e63e6282895643f08d00ff4d81c",
        "0xc4e231fc7988f53363fbc34b3bdef85fed51feae",
        "0xb4524ec5dfb7f881d8cfcd6000367c40fc7abdd4",
        "0xbe3c0b1f33548b668c255fd4f05444e7c2ed46a0",
        "0xa7ac19be672b1744fe580da53ea415b445dfcdab",
        "0x53290bd09ab8f75301782a0e88d0c57fac5f9daf",
        "0x139c61317721388087c00da2917fcc577235b2f4",
        "0x84ef3157344f3c1e6bf624b8de1d66c709c72bac",
        "0x00cbd340fd15e0def8ff3b6ce0d9748b6d3ee517",
        "0x97384ee4f6cbf4928818bd1f071f465b1dca7d4c",
        "0xac3c06e8f1b5e2000e99e438c4319f2a85c3b583",
        "0xc76d55ce92ed36c3bf8fb615c33713eb7d267a5a"
    ],
    "tokens": [
        "native_token",
        "0x2e95cea14dd384429eb3c4331b776c4cfbb6fcd9"
    ]
}