{
    "hash": "0xa35109a8d35f8a3b60eb36cbb3a8965c81a33b03c3bf8b919611917bd027345f",
    "chain": "Binance",
    "U": [
        0,
        2,
        2,
        2,
        2,
        2,
        2,
        2,
        2,
        2,
        2,
        1,
        12,
        13,
        15,
        14
    ],
    "V": [
        1,
        0,
        3,
        4,
        5,
        6,
        7,
        8,
        9,
        10,
        11,
        12,
        13,
        14,
        14,
        0
    ],
    "feat": [
        [
            0,
            0,
            0,
            1,
            0.125,
            0.0625,
            0.3333333333333333,
            0.16666666666666666,
            0.049444946953519864
        ],
        [
            0,
            0,
            1,
            0,
            0.0625,
            0.0625,
            0.16666666666666666,
            0.16666666666666666,
            0.0
        ],
        [
            1,
            0,
            0,
            0,
            0.0,
            0.625,
            0.0,
            0.16666666666666666,
            -1.5507966913474813
        ],
        [
            0,
            0,
            0,
            1,
            0.0625,
            0.0,
            0.16666666666666666,
            0.0,
            0.06855114393106207
        ],
        [
            0,
            0,
            0,
            1,
            0.0625,
            0.0,
            0.16666666666666666,
            0.0,
            0.041402065444928034
        ],
        [
            0,
            0,
            0,
            1,
            0.0625,
            0.0,
            0.16666666666666666,
            0.0,
            0.03076946043832691
        ],
        [
            0,
            0,
            0,
            1,
            0.0625,
            0.0,
            0.16666666666666666,
            0.0,
            0.04721782642807687
        ],
        [
            0,
            0,
            0,
            1,
            0.0625,
            0.0,
            0.16666666666666666,
            0.0,
            0.056901646396745616
        ],
        [
            0,
            0,
            0,
            1,
            0.0625,
            0.0,
            0.16666666666666666,
            0.0,
            2.1808269472566965e-09
        ],
        [
            0,
            0,
            0,
            1,
            0.0625,
            0.0,
            0.16666666666666666,
            0.0,
            1.0
        ],
        [
            0,
            0,
            0,
            1,
            0.0625,
            0.0,
            0.16666666666666666,
            0.0,
            0.14453959549025291
        ],
        [
            0,
            0,
            0,
            1,
            0.0625,
            0.0,
            0.16666666666666666,
            0.0,
            0.11197000408374219
        ],
        [
            0,
            0,
            1,
            0,
            0.0625,
            0.0625,
            0.16666666666666666,
            0.16666666666666666,
            0.0
        ],
        [
            0,
            0,
            1,
            0,
            0.0625,
            0.0625,
            0.16666666666666666,
            0.16666666666666666,
            0.0
        ],
        [
            0,
            1,
            0,
            0,
            0.125,
            0.0625,
            0.3333333333333333,
            0.16666666666666666,
            1.0
        ],
        [
            0,
            0,
            1,
            0,
            0.0,
            0.0625,
            0.0,
            0.16666666666666666,
            -1.0
        ]
    ],
    "nodeCount": 16,
    "edgeCount": 16,
    "tokenCount": 6,
    "nodes": [
        "0x27c03fc59d5e5916747e10be016e784eb6580fc0",
        "0xe2dcc0a934d42dd877da5f18800f4dd088977c7b",
        "0x2f8f107838eeec9b845aa697604f19c780ff088b",
        "0x1cf98210f34cb989be9694de2091ca35dba9d928",
        "0x74d407570b4f5693a830c1a5d0128f21aa23f8fa",
        "0x57880597ffbf82fea5bb975b583d1f845ca497f2",
        "0xf534809422156b79ce9e158178d0397bc9b88514",
        "0x36bd7536fee28adc02c919ee1b75df0410f5d9cf",
        "0xfccc1e64004ba577d4cdc96d5a118c986432b5b1",
        "0x4e902aed4b19db0bdf2c3fe2dafb25b3514ed89a",
        "0x2af04c01655f3be5d075f72de5c845e7225250ed",
        "0x4d23a3a58a37ec1293ad0be10671c4e6ca761dd6",
        "0x2354ef4df11afacb85a5c7f98b624072eccddbb1",
        "0xd99c7f6c65857ac913a8f880a4cb84032ab2fc5b",
        "0x10ed43c718714eb63d5aa57b78b54704e256024e",
        "0xbb4cdb9cbd36b01bd1cbaebf2de08d9173bc095c"
    ],
    "tokens": [
        "0x2fef6fd840b79f0791cc7b93d7fd89fd99fa2332",
        "0x85eac5ac2f758618dfa09bdbe0cf174e7d574d5b",
        "0xe9e7cea3dedca5984780bafc599bd69add087d56",
        "0x8ac76a51cc950d9822d68b83fe1ad97b32cd580d",
        "0xbb4cdb9cbd36b01bd1cbaebf2de08d9173bc095c",
        "native_token"
    ]
}