{
    "hash": "0xb964a95846b0b34787cdec0741fda91a2a527962fd0015da0e30d6d4c10eb2ca",
    "chain": "Ethereum",
    "U": [
        0,
        2
    ],
    "V": [
        1,
        0
    ],
    "feat": [
        [
            0,
            0,
            0,
            1,
            0.5,
            0.5,
            0.5,
            0.5,
            0.0
        ],
        [
            0,
            0,
            0,
            1,
            0.5,
            0.0,
            0.5,
            0.0,
            1.0
        ],
        [
            0,
            1,
            0,
            0,
            0.0,
            0.5,
            0.0,
            0.5,
            -1.0
        ]
    ],
    "nodeCount": 3,
    "edgeCount": 2,
    "tokenCount": 2,
    "nodes": [
        "0x74386381cb384cc0fba0ac669d22f515ffc147d2",
        "0x0000000000000000000000000000000000000000",
        "0x7dccb36ba7177154f364dab07cb57250aba50b3e"
    ],
    "tokens": [
        "0x68037790a0229e9ce6eaa8a99ea92964106c4703",
        "0x90b831fa3bebf58e9744a14d638e25b4ee06f9bc"
    ]
}